moat/lib/mqtt/__init__.py
moat/lib/mqtt/_base_client_state_machine.py
moat/lib/mqtt/_exceptions.py
moat/lib/mqtt/_types.py
moat/lib/mqtt/async_broker.py
moat/lib/mqtt/async_client.py
moat/lib/mqtt/broker_state_machine.py
moat/lib/mqtt/client_state_machine.py
moat/lib/mqtt/py.typed
moat/lib/mqtt/sync_client.py
moat_lib_mqtt-0.8.0.dist-info/licenses/LICENSE
moat_lib_mqtt-0.8.0.dist-info/licenses/LICENSE.txt
moat_lib_mqtt-0.8.0.dist-info/METADATA
moat_lib_mqtt-0.8.0.dist-info/WHEEL
moat_lib_mqtt-0.8.0.dist-info/top_level.txt
moat_lib_mqtt-0.8.0.dist-info/RECORD
